LICENSE
README.rst
setup.py
TestNotification/__init__.py
test_notification_library.egg-info/PKG-INFO
test_notification_library.egg-info/SOURCES.txt
test_notification_library.egg-info/dependency_links.txt
test_notification_library.egg-info/requires.txt
test_notification_library.egg-info/top_level.txt