Metadata-Version: 2.1
Name: test-notification-library
Version: 1.2.1
Summary: Library for sending notifications to different platforms during or after Robot Framework tests execution.
Home-page: https://github.com/barbosamp/robotframework-testnotification.git
Author: Marcos Barbosa
Author-email: mpbarbosa_@outlook.com
License: MIT
Keywords: robotframework testing automation notification
Classifier: Development Status :: 5 - Production/Stable
Classifier: License :: OSI Approved :: MIT License
Classifier: Programming Language :: Python :: 3
Classifier: Programming Language :: Python :: 3.6
Classifier: Programming Language :: Python :: 3.7
Classifier: Programming Language :: Python :: 3.8
Classifier: Programming Language :: Python :: 3.9
Classifier: Programming Language :: Python :: 3.10
Classifier: Operating System :: OS Independent
Requires-Python: >=3.6
License-File: LICENSE
Requires-Dist: requests
Requires-Dist: python-telegram-bot
